setup.py
python_monitor/__init__.py
python_monitor/monitor.py
python_monitor.egg-info/PKG-INFO
python_monitor.egg-info/SOURCES.txt
python_monitor.egg-info/dependency_links.txt
python_monitor.egg-info/requires.txt
python_monitor.egg-info/top_level.txt