Metadata-Version: 1.0
Name: python-monitor
Version: 0.0.1
Summary: monitor your python process
Home-page: https://github.com/Dignn/python_monitor
Author: zhangxiao
Author-email: likezx@163.com
License: MIT Licence
Keywords: pip,python_monitor
Platform: any
